Lab1/constants.svh
`define WORD_SIZE		32

// 7-bit op code values
localparam  [6:0]op 		= 7'b0110011;
localparam  [6:0]op_imm 	= 7'b0010011; 
localparam  [6:0]branch 	= 7'b1100011;
localparam  [6:0]lui		= 7'b0110111;
localparam  [6:0]auipc		= 7'b0010111;
localparam  [6:0]jal		= 7'b1101111;
localparam  [6:0]jalr		= 7'b1100111;
localparam  [6:0]load		= 7'b0000011;
localparam  [6:0]store		= 7'b0100011;

// instruction types
localparam [2:0]INSTRUCTION_TYPE_R	= 3'b000;
localparam [2:0]INSTRUCTION_TYPE_I	= 3'b001;
localparam [2:0]INSTRUCTION_TYPE_S	= 3'b010;
localparam [2:0]INSTRUCTION_TYPE_U	= 3'b011;
localparam [2:0]INSTRUCTION_TYPE_B	= 3'b100;
localparam [2:0]INSTRUCTION_TYPE_J	= 3'b101;

// instructions

// opcode = op
// function 7 + function3
localparam [9:0]ADD = 10'b0000000000;
localparam [9:0]SUB = 10'b0100000000;
localparam [9:0]SLL = 10'b0000000001;
localparam [9:0]SLT = 10'b0000000010;
localparam [9:0]SLTU = 10'b0000000011;
localparam [9:0]XOR = 10'b0000000100;
localparam [9:0]SRL = 10'b0000000101;
localparam [9:0]SRA = 10'b0100000101;
localparam [9:0]OR  = 10'b0000000110;
localparam [9:0]AND = 10'b0000000111;

// opcode = op_imm
// function 3
localparam [2:0]ADDI  = 3'b000;
localparam [2:0]SLTI  = 3'b010;
localparam [2:0]SLTIU = 3'b011; 
localparam [2:0]XORI  = 3'b100;
localparam [2:0]ORI	  = 3'b110;
localparam [2:0]ANDI  = 3'b111;
localparam [2:0]SLLI  = 3'b001;
localparam [2:0]SRLI  = 3'b101;		// SRLI and SRAI has the same value
localparam [2:0]SRAI  = 3'b101;		// need to check their imm[11:5] values

// opcode = branch
localparam [2:0]BEQ  = 3'b000;
localparam [2:0]BNE  = 3'b001;
localparam [2:0]BLT  = 3'b100;
localparam [2:0]BGE  = 3'b101;
localparam [2:0]BLTU = 3'b110;
localparam [2:0]BGEU = 3'b111;

// opcode = load
// function 3
localparam [2:0]LB  = 3'b000;
localparam [2:0]LH  = 3'b001;
localparam [2:0]LW  = 3'b010;
localparam [2:0]LBU = 3'b100;
localparam [2:0]LHU = 3'b101;

// opcode = store
// function 3
localparam [2:0]SB  = 3'b000;
localparam [2:0]SH  = 3'b001;
localparam [2:0]SW  = 3'b010;
localparam [2:0]SBU = 3'b100;
localparam [2:0]SHU = 3'b101;

// control signals for alu is defined here
// 4 operations : 1)op 2) op-imm 3) branch 4) load 5) store
//for op
localparam [4:0]ALU_ADD_I	= 5'b00000; // addi (op imm)
localparam [4:0]ALU_SUB_I	= 5'b00001;
localparam [4:0]ALU_AND_I	= 5'b00010;
localparam [4:0]ALU_OR_I	= 5'b00011;
localparam [4:0]ALU_XOR_I	= 5'b00100;
localparam [4:0]ALU_SLL_I	= 5'b00101; // shift left logical 
localparam [4:0]ALU_SRL_I	= 5'b00110;
localparam [4:0]ALU_SRA_I	= 5'b00111;

localparam [4:0]ALU_BEQ		= 5'b01000;	// branch operations
localparam [4:0]ALU_BNE		= 5'b01001;
localparam [4:0]ALU_BLT		= 5'b01010;
localparam [4:0]ALU_BGE		= 5'b01011;
localparam [4:0]ALU_BLT_U	= 5'b01100;
localparam [4:0]ALU_BGE_U	= 5'b01101;

localparam [4:0]ALU_SLT_I	= 5'b01110;	// set less than operations
localparam [4:0]ALU_SLT_I_U = 5'b01111;	
localparam [4:0]ALU_JAL_R	= 5'b10000;
localparam [4:0]ALU_LUI		= 5'b10001;
localparam [4:0]ALU_AUIPC	= 5'b10010;

// alu immediate read signals
localparam [1:0]ALU_READ_RS2		= 2'b00;
localparam [1:0]ALU_READ_IMM		= 2'b01;
localparam [1:0]ALU_READ_IMM_U		= 2'b10;
localparam [1:0]ALU_READ_IMM_J		= 2'b11;

// xfer_size
localparam [1:0]XFER_BYTE 	= 2'b00;
localparam [1:0]XFER_HALF	= 2'b01;
localparam [1:0]XFER_WORD	= 2'b10;

// register file write select
localparam [1:0]REG_WR_OFF  = 2'b00;
localparam [1:0]REG_WR_ALU  = 2'b01;
localparam [1:0]REG_WR_MEM  = 2'b10;

Lab1/alu.sv
 // control signal mapping are in constants.svh

// alu_signal from regfile_datapath.sv inputs alu_signal as control 
// register inputs read_out_1 and in_2 as in_1 and in_2


// TODO: add an enable signal, alu is not running @ every clock cycle

`define WORD_SIZE	32

module alu(clk, reset, pc, control, in_1, in_2, imm, imm_U_J, imm_en, out, take_branch);
	`include "constants.svh"

	input logic clk, reset;

	input logic [4:0]control;							// 3-bit control signal for ALU 
	input logic [`WORD_SIZE - 1:0]in_1, in_2;			// signed inputs
	input logic [`WORD_SIZE - 1:0]pc;
	input logic [1:0]imm_en;
	input logic [11:0]imm;
	input logic [19:0]imm_U_J;
	output logic [`WORD_SIZE - 1:0]out; 
	output logic take_branch;

	// logics for buffering
	logic [4:0]control_delay;							// 3-bit control signal for ALU 
	logic [`WORD_SIZE - 1:0]pc_delay_1, pc_delay_2;
	logic [1:0]imm_en_delay;
	logic [11:0]imm_delay;
	logic [19:0]imm_U_J_delay;
	
	// dff delay
	always_ff@(posedge clk) begin
		control_delay <= control;

		pc_delay_1 <= pc;
		pc_delay_2 <= pc_delay_1;
		
		imm_en_delay <= imm_en;

		imm_delay <= imm;

		imm_U_J_delay <= imm_U_J;
	end



	logic [`WORD_SIZE - 1:0]sorted_in_2;
	// this combinational logic act as the mux
	always_comb begin
		case(imm_en_delay)
		ALU_READ_RS2:		sorted_in_2 = in_2;	
		ALU_READ_IMM: begin
			// sign extenting the immediate
			if (imm_delay[11]) sorted_in_2[`WORD_SIZE - 1:12] = 20'hfffff;
			else sorted_in_2[`WORD_SIZE - 1:12] = 20'b0;

			sorted_in_2[11:0] = imm_delay;
		end
		ALU_READ_IMM_J: begin
			sorted_in_2 = 32'b0;
		end
		ALU_READ_IMM_U: begin
			sorted_in_2[`WORD_SIZE - 1:12] = imm_U_J_delay; 
			sorted_in_2[11:0] = 12'd0;
		end
		default: begin
			sorted_in_2 = 32'b0;
		end
		endcase
	end

	// temp variable for less than operations
	logic [`WORD_SIZE - 1:0]less_than_temp;
	always_comb begin
		less_than_temp = in_1 - in_2;
	end

	logic signed [`WORD_SIZE - 1 :0]in_1_signed;
	assign in_1_signed = in_1;

	// dff logic
	always_ff@(posedge clk) begin
		if (reset) begin
			out <= 32'd0;
			take_branch <= 0;
		end else begin
			case(control_delay) 
			ALU_ADD_I: begin
				out 		<= in_1 + sorted_in_2;
				take_branch <= 0;
			end
			ALU_SUB_I: begin
				out 		<= in_1 - sorted_in_2;
				take_branch <= 0; 
			end 
			ALU_AND_I: begin
				out 		<= in_1 & sorted_in_2;
				take_branch <= 0; 
			end 
			ALU_OR_I: begin
				out 		<= in_1 | sorted_in_2;
				take_branch <= 0; 
			end 
			ALU_XOR_I: begin
				out 		<= in_1 ^ sorted_in_2;
				take_branch <= 0; 
			end 
			ALU_SLL_I: begin  
				out 		<= in_1 << sorted_in_2[4:0];
				take_branch <= 0; 
			end 
			ALU_SRL_I: begin 
				out 		<= in_1 >> sorted_in_2[4:0];
				take_branch <= 0; 
			end 
			ALU_SRA_I: begin 
				if (in_1[31]) begin
					out <= in_1_signed >>> sorted_in_2[4:0];
				end else begin
					out <= in_1 >> sorted_in_2[4:0];
				end
				take_branch <= 0; 
			end 
			ALU_BEQ: begin	
				out <= 32'dx;
				if (in_1 == sorted_in_2)	take_branch <= 1;
				else						take_branch <= 0;
			end 
			ALU_BNE: begin
				out <= 32'dx;
				if (in_1 != sorted_in_2)	take_branch <= 1;
				else						take_branch <= 0;
			end
			ALU_BLT: begin 
				out <= 32'dx; 	
				if (less_than_temp[31])		take_branch <= 1;
				else						take_branch <= 0;
			end 
			ALU_BGE: begin
				out <= 32'dx;
				if (less_than_temp[31])		take_branch <= 0;
				else						take_branch <= 1;
			end 
			ALU_BLT_U: begin
				out <= 32'dx;
				if (in_1 < sorted_in_2)		take_branch <= 1;
				else						take_branch <= 0;
			end 
			ALU_BGE_U: begin
				out <= 32'dx;
				if (in_1 >= sorted_in_2)	take_branch <= 1;
				else						take_branch <= 0;
			end 
			ALU_SLT_I: begin 
				take_branch <= 0;
				if (less_than_temp[31])		out <= 32'd1;
				else						out <= 32'd0;
			end 
			ALU_SLT_I_U: begin
				take_branch <= 0;
				if (in_1 < sorted_in_2)		out <= 32'd1;
				else						out <= 32'd0;
			end
			ALU_JAL_R: begin
				take_branch <= 1;
				out <= pc_delay_2 + 32'd4;
			end
			ALU_LUI: begin
				take_branch <= 0;
				out <= sorted_in_2;
			end
			ALU_AUIPC: begin
				take_branch <= 1;
				out <= pc_delay_2 + sorted_in_2;
			end
			default: begin
				take_branch <= 1'bx;
				out <= 32'bx;
			end
			endcase
		end
	end

endmodule

Lab1/alu_tb.sv
`define WORD_SIZE		32

module alu_tb();
	`include "constants.svh"
	logic clk, reset;
	logic [3:0]control;
	logic take_branch;
	logic signed [`WORD_SIZE - 1:0]in_1, in_2;
	logic signed [`WORD_SIZE - 1:0]out;

	// dut
	alu alu_dut(.clk(clk), .reset(reset), .control(control),
				.in_1(in_1), .in_2(in_2), .out(out), .take_branch(take_branch));

	// set up clock
	parameter CLOCK_PERIOD = 100;
	initial begin
		clk <= 0;
		forever #(CLOCK_PERIOD / 2) clk <= ~clk;
	end

	// output vars
	initial begin
		$dumpfile("alu.vcd");
		$dumpvars(0, clk, reset, control, in_1, in_2, out, take_branch);
	end

	// tests
	initial begin
		reset <= 1;														@(posedge clk);
		// addition
		reset <= 0; 
		control <= ALU_ADD_I; in_1 <= 32'd9; in_2 <= 32'd11;			@(posedge clk);	
		// subtraction, result is negative
		control <= ALU_SUB_I;											@(posedge clk);
		// subtraction, result is positive
		in_1 <= 32'd11; in_2 <= 32'd9;									@(posedge clk);
		// and
		control <= ALU_AND_I; in_1 <= -32'd1; in_2 <= 32'd0;			@(posedge clk);
		// or
		control <= ALU_OR_I; 											@(posedge clk);
		// xor
		control <= ALU_XOR_I; in_1 <= -32'd1; in_2 <= -32'd1;			@(posedge clk);
		// sl
		control <= ALU_SLL_I; in_1 <= 32'd30; in_2 <= 32'd5;			@(posedge clk);
		// srl
		control <= ALU_SRL_I;											@(posedge clk);
		// sra
		control <= ALU_SRA_I;											@(posedge clk);
		// branch if equal
		control <= ALU_BEQ; in_1 <= 32'd10; in_2 <= 32'd10;				@(posedge clk);
		// branch if not equal
		control <= ALU_BNE; in_1 <= -32'd9; in_2 <= 32'd9;				@(posedge clk);
		// branch if less than
		control <= ALU_BLT;												@(posedge clk);
		// branch if greater equal
		control <= ALU_BGE; in_1 <= -32'd20; in_2 <= -32'd30;			@(posedge clk);
		// branch if less than unsigned
		control <= ALU_BLT_U; in_1 <= 32'd10; in_2 <= 32'hffffff00;		@(posedge clk);
		// branch if greater equal unsigned
		control <= ALU_BGE_U; in_1 <= 32'hffffff00; in_2 <= 32'd10;		@(posedge clk);
		// set less than
		control <= ALU_SLT_I; in_1 <= -32'd10; in_2 <= 32'd90;			@(posedge clk);
		// set less than unsigned
		control <= ALU_SLT_I_U; in_1 <= 32'd10; in_2 <= 32'hffffff00;	@(posedge clk);
																		@(posedge clk);
		$finish;
	end

endmodule

Lab1/alu.vcd
$date
	Wed Feb 17 04:02:52 2021
$end
$version
	Icarus Verilog
$end
$timescale
	1s
$end
$scope module alu_tb $end
$var reg 1 ! clk $end
$upscope $end
$scope module alu_tb $end
$var reg 1 " reset $end
$upscope $end
$scope module alu_tb $end
$var reg 4 # control [3:0] $end
$upscope $end
$scope module alu_tb $end
$var reg 32 $ in_1 [31:0] $end
$upscope $end
$scope module alu_tb $end
$var reg 32 % in_2 [31:0] $end
$upscope $end
$scope module alu_tb $end
$var wire 32 & out [31:0] $end
$upscope $end
$scope module alu_tb $end
$var wire 1 ' take_branch $end
$upscope $end
$enddefinitions $end
#0
$dumpvars
x'
bx &
bx %
bx $
bx #
1"
0!
$end
#50
0'
b0 &
b1011 %
b1001 $
b0 #
0"
1!
#100
0!
#150
b1 #
b10100 &
1!
#200
0!
#250
b11111111111111111111111111111110 &
b1001 %
b1011 $
1!
#300
0!
#350
b0 %
b11111111111111111111111111111111 $
b10 #
b10 &
1!
#400
0!
#450
b0 &
b11 #
1!
#500
0!
#550
b11111111111111111111111111111111 %
b100 #
b11111111111111111111111111111111 &
1!
#600
0!
#650
b0 &
b101 %
b11110 $
b101 #
1!
#700
0!
#750
b110 #
b1111000000 &
1!
#800
0!
#850
b0 &
b111 #
1!
#900
0!
#950
b1010 %
b1010 $
b1000 #
1!
#1000
0!
#1050
1'
b1001 %
b11111111111111111111111111110111 $
b1001 #
1!
#1100
0!
#1150
b1010 #
1!
#1200
0!
#1250
b11111111111111111111111111100010 %
b11111111111111111111111111101100 $
b1011 #
1!
#1300
0!
#1350
b11111111111111111111111100000000 %
b1010 $
b1100 #
1!
#1400
0!
#1450
b1010 %
b11111111111111111111111100000000 $
b1101 #
1!
#1500
0!
#1550
b1011010 %
b11111111111111111111111111110110 $
b1110 #
1!
#1600
0!
#1650
b1 &
0'
b11111111111111111111111100000000 %
b1010 $
b1111 #
1!
