Lab1/instruction_memory.sv
// module for clocked instruction memeory
// instruction memory is 4kiB, which is 32768 bits
// which holds 1024 32-bit instructions

// Upduino only has 1Mb SPRAM, 120Kb DPRAM
`define NUMBER_OF_INSTRUCTIONS	1024
`define WORD_SIZE				32
`define INPUT_FILE				"./assets/instruction_memory.txt"

module instruction_memory(clk, reset, address, instruction);
	localparam address_size = $clog2(`NUMBER_OF_INSTRUCTIONS);

	input logic 	clk, reset;
	input logic 	[`WORD_SIZE - 1:0]address;		// 32-bit address
	output logic 	[`WORD_SIZE - 1:0]instruction;	// 4-byte instruction
	
	// instruction memeory
	logic [31:0] instruction_memory[`NUMBER_OF_INSTRUCTIONS - 1:0];

	// initialize binary memory file
	initial $display("Loading instruction memory...");
	initial $readmemb(`INPUT_FILE, instruction_memory);

	// dff
	always_ff@(posedge clk) begin
		if (reset) begin 
			instruction <= 32'bx;
		end else begin 
			// make sure address is not out of bound
			// assert(address <= `NUMBER_OF_INSTRUCTIONS);
			instruction <= instruction_memory[address/4];
		end
	end
endmodule

Lab1/instruction_memory_tb.sv
module instruction_memory_tb();
	localparam NUMBER_OF_INSTRUCTIONS = 1024;
	localparam address_size = $clog2(NUMBER_OF_INSTRUCTIONS);
	localparam WORD_SIZE = 32;

	logic clk, reset;
	logic [WORD_SIZE - 1:0]address;
	logic [WORD_SIZE - 1:0]instruction;

	// dut
	instruction_memory imem (.clk, .reset, .address, .instruction);

	// initialize clock
	parameter CLOCK_PERIOD = 100;
	initial begin
		clk <= 0;
		forever #(CLOCK_PERIOD / 2) clk <= ~clk;
	end

	initial begin
		$dumpfile("instruction_memory.vcd");
		$dumpvars(0, clk, reset, address, instruction);
	end

	// tests
	initial begin
		address <= 32'd0; reset <= 1; 	@(posedge clk);
		reset <= 0;						@(posedge clk);
		// let it read the memory file
		// cycle through every location and making sure it is right
										@(posedge clk);
										@(posedge clk);
		address <= 32'd0;				@(posedge clk);
		address <= 32'd1;				@(posedge clk);
		address <= 32'd2;				@(posedge clk);
		address <= 32'd3;				@(posedge clk);
		address <= 32'd4;				@(posedge clk);
		address <= 32'd5;				@(posedge clk);
		address <= 32'd6;				@(posedge clk);
		address <= 32'd7;				@(posedge clk);
		address <= 32'd8;				@(posedge clk);
		address <= 32'd9;				@(posedge clk);
		address <= 32'd10;				@(posedge clk);
		address <= 32'd11;				@(posedge clk);
		address <= 32'd12;				@(posedge clk);
		address <= 32'd13;				@(posedge clk);
		address <= 32'd14;				@(posedge clk);
		address <= 32'd15;				@(posedge clk);
		address <= 32'd16;				@(posedge clk);
		address <= 32'd17;				@(posedge clk);
		// checking for out of bounds condition
		// when address exceeds instruction memory size
		//address <= 32'hffffff;	@(posedge clk);
		$finish;
	end
endmodule

Lab1/instruction_memory.vcd
$date
	Sat Feb 13 17:27:10 2021
$end
$version
	Icarus Verilog
$end
$timescale
	1s
$end
$scope module instruction_memory_tb $end
$var reg 1 ! clk $end
$upscope $end
$scope module instruction_memory_tb $end
$var reg 1 " reset $end
$upscope $end
$scope module instruction_memory_tb $end
$var reg 32 # address [31:0] $end
$upscope $end
$scope module instruction_memory_tb $end
$var wire 32 $ instruction [31:0] $end
$upscope $end
$enddefinitions $end
#0
$dumpvars
bx $
b0 #
1"
0!
$end
#50
b0 $
0"
1!
#100
0!
#150
1!
#200
0!
#250
1!
#300
0!
#350
1!
#400
0!
#450
b1 #
1!
#500
0!
#550
b10 #
b1 $
1!
#600
0!
#650
b10 $
b11 #
1!
#700
0!
#750
b100 #
b11 $
1!
#800
0!
#850
b100 $
b101 #
1!
#900
0!
#950
b110 #
b101 $
1!
#1000
0!
#1050
b110 $
b111 #
1!
#1100
0!
#1150
b1000 #
b111 $
1!
#1200
0!
#1250
b1000 $
b1001 #
1!
#1300
0!
#1350
b1010 #
b1001 $
1!
#1400
0!
#1450
b1010 $
b1011 #
1!
#1500
0!
#1550
b1100 #
b1011 $
1!
#1600
0!
#1650
b1100 $
b1101 #
1!
#1700
0!
#1750
b1110 #
b1101 $
1!
#1800
0!
#1850
b1110 $
b1111 #
1!
#1900
0!
#1950
b10000 #
b1111 $
1!
#2000
0!
#2050
b10000 $
b10001 #
1!
#2100
0!
#2150
b10001 $
1!
