upduino/alu_signal.svh
// control signals for alu is defined here

localparam [2:0]ALU_ADD = 3'b000;
localparam [2:0]ALU_SUB = 3'b001;
localparam [2:0]ALU_AND = 3'b010;
localparam [2:0]ALU_OR  = 3'b011;
localparam [2:0]ALU_XOR = 3'b100;
localparam [2:0]ALU_SL  = 3'b101;
localparam [2:0]ALU_SRL = 3'b110;
localparam [2:0]ALU_SRA = 3'b111;

upduino/alu.sv
// alu performs the following operations
// - add
// - sub
// - and
// - or
// - xor 
// - shift left
// - shift right logical
// - shift right arithmetic

// control signal mapping:
// ALU_ADD -- 000
// ALU_SUB -- 001
// ALU_AND -- 010
// ALU_OR  -- 011
// ALU_XOR -- 100
// ALU_SL  -- 101
// ALU_SRL -- 110
// ALU_SRA -- 111


`include "alu_signal.svh"
`define WORD_SIZE	32

module alu(clk, reset, control, in_1, in_2, out);
	input logic clk, reset;
	input logic [2:0]control;							// 3-bit control signal for ALU operation
	input logic signed [`WORD_SIZE - 1:0]in_1, in_2;	// signed inputs

	output logic signed [`WORD_SIZE - 1:0]out;



	// dff logic
	always_ff@(posedge clk) begin
		if (reset) begin
			out <= 32'd0;
		end else if (control == ALU_ADD) begin
			out <= in_1 + in_2;
		end else if (control == ALU_SUB) begin
			out <= in_1 - in_2;
		end else if (control == ALU_AND) begin
			out <= in_1 & in_2;
		end else if (control == ALU_OR) begin
			out <= in_1 | in_2;
		end else if (control == ALU_XOR) begin
			out <= in_1 ^ in_2;
		end else if (control == ALU_SL) begin
			// shift left in_1 by in_2 bits
			out <= in_1 << in_2;
		end else if (control == ALU_SRL) begin
			// logical shift right in_1 by in_2 bits
			out <= in_1 >> in_2;
		end else begin
			// arithmetic shift right in_1 by in_2 bits
			out <= in_1 >>> in_2;
		end
	end

endmodule

upduino/alu_tb.sv
`define WORD_SIZE		32

module alu_tb();
	logic clk, reset;
	logic [2:0]control;
	logic signed [`WORD_SIZE - 1:0]in_1, in_2;
	logic signed [`WORD_SIZE - 1:0]out;

	// dut
	alu alu_dut(.clk(clk), .reset(reset), .control(control),
				.in_1(in_1), .in_2(in_2), .out(out));

	// set up clock
	parameter CLOCK_PERIOD = 100;
	initial begin
		clk <= 0;
		forever #(CLOCK_PERIOD / 2) clk <= ~clk;
	end

	// output vars
	initial begin
		$dumpfile("alu.vcd");
		$dumpvars(0, clk, reset, control, in_1, in_2, out);
	end

	// tests
	initial begin
		reset <= 1;														@(posedge clk);
		// addition
		reset <= 0; control <= 3'b000; in_1 <= 32'd9; in_2 <= 32'd11;	@(posedge clk);	
		// subtraction
		control <= 3'b001;												@(posedge clk);
		in_1 <= 32'd11; in_2 <= 32'd9;									@(posedge clk);
		// and
		control <= 3'b010; in_1 <= -32'd1; in_2 <= 32'd0;				@(posedge clk);
		// or
		control <= 3'b011; 												@(posedge clk);
		// xor
		control <= 3'b100; in_1 <= -32'd1; in_2 <= -32'd1;				@(posedge clk);
		// sl
		control <= 3'b101; in_1 <= 32'd30; in_2 <= 32'd5;				@(posedge clk);
		// srl
		control <= 3'b110;												@(posedge clk);
		// sra
		control <= 3'b111;												@(posedge clk);
																		@(posedge clk);
		$finish;
	end

endmodule

upduino/alu.vcd
$date
	Sun Feb 14 23:46:44 2021
$end
$version
	Icarus Verilog
$end
$timescale
	1s
$end
$scope module alu_tb $end
$var reg 1 ! clk $end
$upscope $end
$scope module alu_tb $end
$var reg 1 " reset $end
$upscope $end
$scope module alu_tb $end
$var reg 3 # control [2:0] $end
$upscope $end
$scope module alu_tb $end
$var reg 32 $ in_1 [31:0] $end
$upscope $end
$scope module alu_tb $end
$var reg 32 % in_2 [31:0] $end
$upscope $end
$scope module alu_tb $end
$var wire 32 & out [31:0] $end
$upscope $end
$enddefinitions $end
#0
$dumpvars
bx &
bx %
bx $
bx #
1"
0!
$end
#50
b0 &
b1011 %
b1001 $
b0 #
0"
1!
#100
0!
#150
b1 #
b10100 &
1!
#200
0!
#250
b11111111111111111111111111111110 &
b1001 %
b1011 $
1!
#300
0!
#350
b0 %
b11111111111111111111111111111111 $
b10 #
b10 &
1!
#400
0!
#450
b0 &
b11 #
1!
#500
0!
#550
b11111111111111111111111111111111 %
b100 #
b11111111111111111111111111111111 &
1!
#600
0!
#650
b0 &
b101 %
b11110 $
b101 #
1!
#700
0!
#750
b110 #
b1111000000 &
1!
#800
0!
#850
b0 &
b111 #
1!
